swaymons/__init__.py
swaymons/__main__.py
swaymons-0.1.0.dist-info/entry_points.txt
swaymons-0.1.0.dist-info/WHEEL
swaymons-0.1.0.dist-info/METADATA
swaymons-0.1.0.dist-info/RECORD
